setup.py
distributions/Binomialdistribution.py
distributions/Gaussiandistribution.py
distributions/Generaldistribution.py
distributions/__init__.py
py_data_distributions.egg-info/PKG-INFO
py_data_distributions.egg-info/SOURCES.txt
py_data_distributions.egg-info/dependency_links.txt
py_data_distributions.egg-info/not-zip-safe
py_data_distributions.egg-info/top_level.txt